omnichannel/__init__.py
omnichannel/client.py
omnichannel/exceptions.py
mts_client-0.2.3.dist-info/METADATA
mts_client-0.2.3.dist-info/WHEEL
mts_client-0.2.3.dist-info/RECORD
